Metadata-Version: 2.1
Name: odoo-addon-account_payment_widget_amount
Version: 18.0.1.0.0.2
Requires-Python: >=3.10
Requires-Dist: odoo==18.0.*
Summary: Extends the payment widget to be able to choose the payment amount
Home-page: https://github.com/OCA/account-payment
License: AGPL-3
Author: ForgeFlow S.L., OERP Canada, Odoo Community Association (OCA)
Author-email: support@odoo-community.org
Classifier: Programming Language :: Python
Classifier: Framework :: Odoo
Classifier: Framework :: Odoo :: 18.0
Classifier: License :: OSI Approved :: GNU Affero General Public License v3
